{
  "job_openings": [
    {
      "job_title": "Junior Software Developer",
      "designation": "Engineer",
      "department": "Development"
    },
    {
      "job_title": "Senior Business Analyst",
      "designation": "Business Analyst",
      "department": "Business Development"
    },
    {
      "job_title": "Cloud Solutions Engineer",
      "designation": "Engineer",
      "department": "Cloud Services"
    },
    {
      "job_title": "Cybersecurity Analyst",
      "designation": "Analyst",
      "department": "Cybersecurity"
    },
    {
      "job_title": "Customer Support Specialist",
      "designation": "Customer Service Representative",
      "department": "Customer Service"
    },
    {
      "job_title": "Data Scientist",
      "designation": "Analyst",
      "department": "Data Analytics"
    },
    {
      "job_title": "Database Administrator",
      "designation": "Engineer",
      "department": "Database Management"
    },
    {
      "job_title": "IT Support Technician",
      "designation": "Analyst",
      "department": "IT Support"
    },
    {
      "job_title": "Operations Manager",
      "designation": "Manager",
      "department": "Operations"
    },
    {
      "job_title": "HR Assistant",
      "designation": "Administrative Assistant",
      "department": "Human Resources"
    },
    {
      "job_title": "Digital Marketing Specialist",
      "designation": "Designer",
      "department": "Marketing"
    },
    {
      "job_title": "Network Administrator",
      "designation": "Engineer",
      "department": "Network Administration"
    },
    {
      "job_title": "Senior Finance Manager",
      "designation": "Finance Manager",
      "department": "Accounts"
    },
    {
      "job_title": "Legal Consultant",
      "designation": "Consultant",
      "department": "Legal"
    },
    {
      "job_title": "Chief Technology Officer",
      "designation": "Chief Technology Officer",
      "department": "Management"
    },
    {
      "job_title": "Business Development Associate",
      "designation": "Associate",
      "department": "Business Development"
    },
    {
      "job_title": "Executive Assistant to CEO",
      "designation": "Executive Assistant",
      "department": "Management"
    },
    {
      "job_title": "Marketing Coordinator",
      "designation": "Administrative Officer",
      "department": "Marketing"
    },
    {
      "job_title": "Senior Cloud Consultant",
      "designation": "Consultant",
      "department": "Cloud Services"
    },
    {
      "job_title": "Sales Engineer",
      "designation": "Engineer",
      "department": "Business Development"
    },
    {
      "job_title": "Recruitment Specialist",
      "designation": "HR Manager",
      "department": "Human Resources"
    }
  ],
  "company_name": "Acme Inc.",
  "generated_count": 20,
  "theme_subject": "a IT outsourcing company",
  "generated_at": "2025-06-04T16:45:45.570259",
  "departments_context": [
    "Accounts",
    "Business Development",
    "Cloud Services",
    "Customer Service",
    "Customer Service",
    "Cybersecurity",
    "Data Analytics",
    "Database Management",
    "Development",
    "Dispatch",
    "Human Resources",
    "Human Resources",
    "IT Support",
    "Legal",
    "Management",
    "Management",
    "Marketing",
    "Marketing",
    "Network Administration",
    "Operations"
  ],
  "designations_context": [
    "Accountant",
    "Administrative Assistant",
    "Administrative Officer",
    "Analyst",
    "Associate",
    "Business Analyst",
    "Business Development Manager",
    "Consultant",
    "Chief Executive Officer",
    "Chief Financial Officer",
    "Chief Operating Officer",
    "Chief Technology Officer",
    "Customer Service Representative",
    "Designer",
    "Engineer",
    "Executive Assistant",
    "Finance Manager",
    "HR Manager",
    "Head of Marketing and Sales",
    "Manager"
  ]
}